kontur/httptoolkitcore/__init__.py
kontur/httptoolkitcore/_version.py
kontur/httptoolkitcore/encoder.py
kontur/httptoolkitcore/errors.py
kontur/httptoolkitcore/header.py
kontur/httptoolkitcore/http_method.py
kontur/httptoolkitcore/request.py
kontur/httptoolkitcore/retry.py
kontur/httptoolkitcore/sent_request.py
kontur/httptoolkitcore/sent_request_log_record.py
kontur/httptoolkitcore/httpx_service/__init__.py
kontur/httptoolkitcore/httpx_service/_async.py
kontur/httptoolkitcore/httpx_service/_sync.py
kontur/httptoolkitcore/response/__init__.py
kontur/httptoolkitcore/response/_base.py
kontur/httptoolkitcore/response/_regular.py
kontur/httptoolkitcore/response/_stream/__init__.py
kontur/httptoolkitcore/response/_stream/_async.py
kontur/httptoolkitcore/response/_stream/_sync.py
kontur/httptoolkitcore/service/__init__.py
kontur/httptoolkitcore/service/_async.py
kontur/httptoolkitcore/service/_sync.py
kontur/httptoolkitcore/transport/__init__.py
kontur/httptoolkitcore/transport/_async_base.py
kontur/httptoolkitcore/transport/_sync_base.py
kontur/httptoolkitcore/transport/_httpx/__init__.py
kontur/httptoolkitcore/transport/_httpx/_async.py
kontur/httptoolkitcore/transport/_httpx/_base.py
kontur/httptoolkitcore/transport/_httpx/_sync.py
kontur/httptoolkitcore/transport/_httpx/_session/__init__.py
kontur/httptoolkitcore/transport/_httpx/_session/_async.py
kontur/httptoolkitcore/transport/_httpx/_session/_sync.py
kontur/httptoolkitcoreopentelemetry/__init__.py
kontur/httptoolkitcoreopentelemetry/_instrumentation.py
kontur/httptoolkitcoreopentelemetry/example/client.py
kontur_http_toolkit_core-1.0.0.dev1.dist-info/METADATA
kontur_http_toolkit_core-1.0.0.dev1.dist-info/WHEEL
kontur_http_toolkit_core-1.0.0.dev1.dist-info/entry_points.txt
kontur_http_toolkit_core-1.0.0.dev1.dist-info/top_level.txt
kontur_http_toolkit_core-1.0.0.dev1.dist-info/RECORD
