Metadata-Version: 2.1
Name: kontur-http-toolkit-core
Version: 1.0.0.dev1
Summary: Библиотека для создания HTTP-клиентов к различным сервисам на основе HTTPX
Project-URL: homepage, https://github.com/skbkontur/http_toolkit
Requires-Python: <3.13,>=3.8
Requires-Dist: httpx~=0.24.1
Provides-Extra: instruments
Requires-Dist: httpx~=0.24.1; extra == "instruments"
Provides-Extra: opentelemetry
Requires-Dist: opentelemetry-instrumentation-httpx; extra == "opentelemetry"
Provides-Extra: test
Requires-Dist: pytest==7.0.0; extra == "test"
Requires-Dist: pytest-cov==3.0.0; extra == "test"
Requires-Dist: testfixtures==6.18.3; extra == "test"
Requires-Dist: pytest-asyncio==0.18.3; extra == "test"
Requires-Dist: pytest-httpx==0.22.0; extra == "test"
